{
  "phase": "final_verification",
  "cargo_build_passed": true,
  "cargo_test_passed": true,
  "readme_artifact_check": "pass",
  "markdown_link_check": "pass",
  "codegraph_help_passed": true,
  "fixture_index_passed": true,
  "json_validation_errors": [],
  "json_validation_passed": true,
  "final_comparison_report_exists": true,
  "latest_comparison_report_exists": true,
  "commands": [
    {
      "name": "phase10_cargo_build_workspace",
      "command": [
        "cargo",
        "build",
        "--workspace"
      ],
      "cwd": "<REPO_ROOT>",
      "exit_code": 0,
      "timed_out": false,
      "started_at": "2026-05-14T01:07:31-05:00",
      "ended_at": "2026-05-14T01:07:31-05:00",
      "duration_ms": 194,
      "stdout": "reports/comparison/cgc_full_run/logs/phase10_cargo_build_workspace.stdout.txt",
      "stderr": "reports/comparison/cgc_full_run/logs/phase10_cargo_build_workspace.stderr.txt",
      "stdout_bytes": 0,
      "stderr_bytes": 123
    },
    {
      "name": "phase10_cargo_test_workspace",
      "command": [
        "cargo",
        "test",
        "--workspace"
      ],
      "cwd": "<REPO_ROOT>",
      "exit_code": 0,
      "timed_out": false,
      "started_at": "2026-05-14T01:07:31-05:00",
      "ended_at": "2026-05-14T01:08:12-05:00",
      "duration_ms": 40493,
      "stdout": "reports/comparison/cgc_full_run/logs/phase10_cargo_test_workspace.stdout.txt",
      "stderr": "reports/comparison/cgc_full_run/logs/phase10_cargo_test_workspace.stderr.txt",
      "stdout_bytes": 29502,
      "stderr_bytes": 1527
    },
    {
      "name": "phase10_check_readme_artifacts",
      "command": [
        "python",
        "scripts/check_readme_artifacts.py"
      ],
      "cwd": "<REPO_ROOT>",
      "exit_code": 0,
      "timed_out": false,
      "started_at": "2026-05-14T01:08:12-05:00",
      "ended_at": "2026-05-14T01:08:12-05:00",
      "duration_ms": 55,
      "stdout": "reports/comparison/cgc_full_run/logs/phase10_check_readme_artifacts.stdout.txt",
      "stderr": "reports/comparison/cgc_full_run/logs/phase10_check_readme_artifacts.stderr.txt",
      "stdout_bytes": 55,
      "stderr_bytes": 0
    },
    {
      "name": "phase10_check_markdown_links",
      "command": [
        "python",
        "scripts/check_markdown_links.py"
      ],
      "cwd": "<REPO_ROOT>",
      "exit_code": 0,
      "timed_out": false,
      "started_at": "2026-05-14T01:08:12-05:00",
      "ended_at": "2026-05-14T01:08:12-05:00",
      "duration_ms": 193,
      "stdout": "reports/comparison/cgc_full_run/logs/phase10_check_markdown_links.stdout.txt",
      "stderr": "reports/comparison/cgc_full_run/logs/phase10_check_markdown_links.stderr.txt",
      "stdout_bytes": 78,
      "stderr_bytes": 0
    },
    {
      "name": "phase10_codegraph_help",
      "command": [
        "cargo",
        "run",
        "--bin",
        "codegraph-mcp",
        "--",
        "--help"
      ],
      "cwd": "<REPO_ROOT>",
      "exit_code": 0,
      "timed_out": false,
      "started_at": "2026-05-14T01:08:12-05:00",
      "ended_at": "2026-05-14T01:08:12-05:00",
      "duration_ms": 131,
      "stdout": "reports/comparison/cgc_full_run/logs/phase10_codegraph_help.stdout.txt",
      "stderr": "reports/comparison/cgc_full_run/logs/phase10_codegraph_help.stderr.txt",
      "stdout_bytes": 1850,
      "stderr_bytes": 177
    },
    {
      "name": "phase10_codegraph_fixture_index",
      "command": [
        "cargo",
        "run",
        "--bin",
        "codegraph-mcp",
        "--",
        "index",
        "<REPO_ROOT>\\fixtures\\smoke\\basic_repo"
      ],
      "cwd": "<REPO_ROOT>",
      "exit_code": 0,
      "timed_out": false,
      "started_at": "2026-05-14T01:08:12-05:00",
      "ended_at": "2026-05-14T01:08:12-05:00",
      "duration_ms": 141,
      "stdout": "reports/comparison/cgc_full_run/logs/phase10_codegraph_fixture_index.stdout.txt",
      "stderr": "reports/comparison/cgc_full_run/logs/phase10_codegraph_fixture_index.stderr.txt",
      "stdout_bytes": 794,
      "stderr_bytes": 251
    }
  ]
}